esbn_pytorch/__init__.py
esbn_pytorch/esbn_pytorch.py
esbn_pytorch-0.0.4.dist-info/LICENSE
esbn_pytorch-0.0.4.dist-info/METADATA
esbn_pytorch-0.0.4.dist-info/WHEEL
esbn_pytorch-0.0.4.dist-info/top_level.txt
esbn_pytorch-0.0.4.dist-info/RECORD
